<?xml version="1.0" encoding="UTF-8"?>
<req>
	<skills>умение задавать вопросы</skills>
	<skills>умение адекватно описывать обнаруженные ошибки</skills>
	<skills>умение писать алгоритмически простые тест-кейсы</skills>
	<skills>умение ранжировать дефекты по важности</skills>
	 <skills>любопытство</skills>
	<skills>дисциплинированность</skills>
	<skills>психологическая гибкость</skills>
	<skills>активность и решимость</skills>
	<skills>работа в команде</skills>
	<skills>поиск информации</skills>
	<skills>тайм-менеджмент</skills>
	<skills>комуникабельность</skills>
	<skills>и многим другим скиллам</skills>
</req>
